colourings/__init__.py
colourings/colour.py
colourings/conversions.py
colourings/definitions.py
colourings/identify.py
colourings/py.typed
colourings-0.4.1.dist-info/licenses/LICENSE.txt
colourings-0.4.1.dist-info/METADATA
colourings-0.4.1.dist-info/WHEEL
colourings-0.4.1.dist-info/top_level.txt
colourings-0.4.1.dist-info/RECORD
