Metadata-Version: 2.4
Name: colourings
Version: 0.4.1
Summary: Colouring in Python
Author-email: Daniel Stoops <danielstoops25@gmail.com>
License: BSD-3-Clause license
Project-URL: Repository, https://github.com/Stoops-ML/colourings
Keywords: color,colour
Classifier: Programming Language :: Python
Classifier: Programming Language :: Python :: 3
Classifier: Programming Language :: Python :: 3.10
Classifier: Programming Language :: Python :: 3.11
Classifier: Programming Language :: Python :: 3.12
Classifier: Programming Language :: Python :: 3.13
Classifier: Programming Language :: Python :: Implementation :: CPython
Classifier: Operating System :: OS Independent
Requires-Python: >=3.10
License-File: LICENSE.txt
Provides-Extra: dev
Requires-Dist: pytest>=8.3.4; extra == "dev"
Requires-Dist: pytest-cov>=6.0.0; extra == "dev"
Requires-Dist: ruff>=0.9.4; extra == "dev"
Requires-Dist: tox>=4.24.1; extra == "dev"
Requires-Dist: build; extra == "dev"
Dynamic: license-file
